{
    "fingerprint_version": 42,
    "timestamp": "2024-06-16T00:24:18.807Z",
    "math_rand": "117b5095b06db4",
    "webasm": true,
    "document": {
        "title": "Document",
        "referrer": ""
    },
    "navigator": {
        "user_agent": "Mozilla/5.0 (Windows NT 10.0; Win64; x64) AppleWebKit/537.36 (KHTML, like Gecko) Chrome/125.0.0.0 Safari/537.36",
        "platform": "Win32",
        "language": "en-US",
        "languages": [
            "en-US",
            "en",
            "fr"
        ],
        "hardware_concurrency": 4,
        "device_memory": 4,
        "product": "Gecko",
        "product_sub": "20030107",
        "vendor": "Google Inc.",
        "vendor_sub": "",
        "webdriver": false,
        "max_touch_points": 0,
        "cookie_enabled": true,
        "property_list": [
            "vendorSub",
            "productSub",
            "vendor",
            "maxTouchPoints",
            "scheduling",
            "userActivation",
            "doNotTrack",
            "geolocation",
            "connection",
            "plugins",
            "mimeTypes",
            "pdfViewerEnabled",
            "webkitTemporaryStorage",
            "webkitPersistentStorage",
            "windowControlsOverlay",
            "hardwareConcurrency",
            "cookieEnabled",
            "appCodeName",
            "appName",
            "appVersion",
            "platform",
            "product",
            "userAgent",
            "language",
            "languages",
            "onLine",
            "webdriver",
            "getGamepads",
            "javaEnabled",
            "sendBeacon",
            "vibrate",
            "deprecatedRunAdAuctionEnforcesKAnonymity",
            "protectedAudience",
            "bluetooth",
            "storageBuckets",
            "clipboard",
            "credentials",
            "keyboard",
            "managed",
            "mediaDevices",
            "storage",
            "serviceWorker",
            "virtualKeyboard",
            "wakeLock",
            "deviceMemory",
            "userAgentData",
            "login",
            "ink",
            "mediaCapabilities",
            "hid",
            "locks",
            "gpu",
            "mediaSession",
            "permissions",
            "presentation",
            "usb",
            "xr",
            "serial",
            "adAuctionComponents",
            "runAdAuction",
            "canLoadAdAuctionFencedFrame",
            "canShare",
            "share",
            "clearAppBadge",
            "getBattery",
            "getUserMedia",
            "requestMIDIAccess",
            "requestMediaKeySystemAccess",
            "setAppBadge",
            "webkitGetUserMedia",
            "clearOriginJoinedAdInterestGroups",
            "createAuctionNonce",
            "deprecatedReplaceInURN",
            "deprecatedURNToURL",
            "getInstalledRelatedApps",
            "joinAdInterestGroup",
            "leaveAdInterestGroup",
            "updateAdInterestGroups",
            "registerProtocolHandler",
            "unregisterProtocolHandler"
        ],
        "connection_rtt": 50
    },
    "web_gl": {
        "canvas_fingerprint": {
            "length": 32206,
            "num_colors": 4675,
            "md5": "043ff0f7640f2ae955226971c5c3ca0f",
            "tlsh": "3FE2E149B95B5705F047A6EB6D35AD8230367D73CC2F5AEC3980F7B13843DA91242CA9"
        },
        "parameters": {
            "renderer": "ANGLE (Intel, Intel(R) HD Graphics 5500 (0x00001616) Direct3D11 vs_5_0 ps_5_0, D3D11)",
            "vendor": "Google Inc. (Intel)"
        }
    },
    "window": {
        "location": {
            "origin": "file://",
            "pathname": "/C:/Users/seka/Documents/talon/index.html",
            "href": "file:///C:/Users/seka/Documents/talon/index.html"
        },
        "history": {
            "length": 1
        },
        "screen": {
            "avail_height": 728,
            "avail_width": 1360,
            "avail_top": 0,
            "height": 768,
            "width": 1360,
            "color_depth": 24
        },
        "performance": {
            "memory": {
                "js_heap_size_limit": 2190000000,
                "total_js_heap_size": 10600000,
                "used_js_heap_size": 10000000
            },
            "resources": []
        },
        "device_pixel_ratio": 1,
        "dark_mode": false,
        "chrome": true,
        "property_list": [
            "window",
            "self",
            "document",
            "name",
            "location",
            "customElements",
            "history",
            "navigation",
            "locationbar",
            "menubar",
            "personalbar",
            "scrollbars",
            "statusbar",
            "toolbar",
            "status",
            "closed",
            "frames",
            "length",
            "top",
            "opener",
            "parent",
            "frameElement",
            "navigator",
            "origin",
            "external",
            "screen",
            "innerWidth",
            "innerHeight",
            "scrollX",
            "pageXOffset",
            "scrollY",
            "pageYOffset",
            "visualViewport",
            "screenX",
            "screenY",
            "outerWidth",
            "outerHeight",
            "devicePixelRatio",
            "clientInformation",
            "screenLeft",
            "screenTop",
            "styleMedia",
            "onsearch",
            "isSecureContext",
            "trustedTypes",
            "performance",
            "onappinstalled",
            "onbeforeinstallprompt",
            "crypto",
            "indexedDB",
            "sessionStorage",
            "localStorage",
            "onbeforexrselect",
            "onabort",
            "onbeforeinput",
            "onbeforematch",
            "onbeforetoggle",
            "onblur",
            "oncancel",
            "oncanplay",
            "oncanplaythrough",
            "onchange",
            "onclick",
            "onclose",
            "oncontentvisibilityautostatechange",
            "oncontextlost",
            "oncontextmenu",
            "oncontextrestored",
            "oncuechange",
            "ondblclick",
            "ondrag",
            "ondragend",
            "ondragenter",
            "ondragleave",
            "ondragover",
            "ondragstart",
            "ondrop",
            "ondurationchange",
            "onemptied",
            "onended",
            "onerror",
            "onfocus",
            "onformdata",
            "oninput",
            "oninvalid",
            "onkeydown",
            "onkeypress",
            "onkeyup",
            "onload",
            "onloadeddata",
            "onloadedmetadata",
            "onloadstart",
            "onmousedown",
            "onmouseenter",
            "onmouseleave",
            "onmousemove",
            "onmouseout",
            "onmouseover",
            "onmouseup",
            "onmousewheel",
            "onpause",
            "onplay",
            "onplaying",
            "onprogress",
            "onratechange",
            "onreset",
            "onresize",
            "onscroll",
            "onsecuritypolicyviolation",
            "onseeked",
            "onseeking",
            "onselect",
            "onslotchange",
            "onstalled",
            "onsubmit",
            "onsuspend",
            "ontimeupdate",
            "ontoggle",
            "onvolumechange",
            "onwaiting",
            "onwebkitanimationend",
            "onwebkitanimationiteration",
            "onwebkitanimationstart",
            "onwebkittransitionend",
            "onwheel",
            "onauxclick",
            "ongotpointercapture",
            "onlostpointercapture",
            "onpointerdown",
            "onpointermove",
            "onpointerrawupdate",
            "onpointerup",
            "onpointercancel",
            "onpointerover",
            "onpointerout",
            "onpointerenter",
            "onpointerleave",
            "onselectstart",
            "onselectionchange",
            "onanimationend",
            "onanimationiteration",
            "onanimationstart",
            "ontransitionrun",
            "ontransitionstart",
            "ontransitionend",
            "ontransitioncancel",
            "onafterprint",
            "onbeforeprint",
            "onbeforeunload",
            "onhashchange",
            "onlanguagechange",
            "onmessage",
            "onmessageerror",
            "onoffline",
            "ononline",
            "onpagehide",
            "onpageshow",
            "onpopstate",
            "onrejectionhandled",
            "onstorage",
            "onunhandledrejection",
            "onunload",
            "crossOriginIsolated",
            "scheduler",
            "alert",
            "atob",
            "blur",
            "btoa",
            "cancelAnimationFrame",
            "cancelIdleCallback",
            "captureEvents",
            "clearInterval",
            "clearTimeout",
            "close",
            "confirm",
            "createImageBitmap",
            "fetch",
            "find",
            "focus",
            "getComputedStyle",
            "getSelection",
            "matchMedia",
            "moveBy",
            "moveTo",
            "open",
            "postMessage",
            "print",
            "prompt",
            "queueMicrotask",
            "releaseEvents",
            "reportError",
            "requestAnimationFrame",
            "requestIdleCallback",
            "resizeBy",
            "resizeTo",
            "scroll",
            "scrollBy",
            "scrollTo",
            "setInterval",
            "setTimeout",
            "stop",
            "structuredClone",
            "webkitCancelAnimationFrame",
            "webkitRequestAnimationFrame",
            "chrome",
            "fence",
            "caches",
            "cookieStore",
            "ondevicemotion",
            "ondeviceorientation",
            "ondeviceorientationabsolute",
            "launchQueue",
            "sharedStorage",
            "documentPictureInPicture",
            "getScreenDetails",
            "queryLocalFonts",
            "showDirectoryPicker",
            "showOpenFilePicker",
            "showSaveFilePicker",
            "originAgentCluster",
            "onpageswap",
            "onpagereveal",
            "credentialless",
            "speechSynthesis",
            "onscrollend",
            "webkitRequestFileSystem",
            "webkitResolveLocalFileSystemURL",
            "regeneratorRuntime",
            "talon",
            "k",
            "i",
            "TEMPORARY",
            "PERSISTENT",
            "addEventListener",
            "dispatchEvent",
            "removeEventListener"
        ]
    },
    "date": {
        "timezone_offset": -120,
        "format": {
            "calendar": "gregory",
            "day": "2-digit",
            "locale": "fr",
            "month": "2-digit",
            "numbering_system": "latn",
            "time_zone": "Europe/Paris",
            "year": "numeric"
        }
    },
    "runtime": {
        "sd_recurse": false
    },
    "fpjs": {
        "version": "3.4.2",
        "visitor_id": "ad14cc632ffc5f2354f1ed3ece760f0c",
        "confidence": 0.6,
        "hashes": {
            "fonts": "431a26e6db1535e739176d16847a1f9a",
            "plugins": "4ec460fe0377b5de12899575d11d37dc",
            "audio": "31bb7487c0967198a47fb29cc1e97237",
            "canvas": "e9918dd97a94dcd54431f344e6f2e564",
            "screen": "c227e20f3d096af0dd85aabb03a28dd0"
        }
    },
    "motion": {
        "mousemove": [
            {
                "t": 453.1999999284744,
                "x": 449,
                "y": 19
            },
            {
                "t": 517,
                "x": 475,
                "y": 54
            }
        ],
        "mousedown": [],
        "mouseup": [],
        "wheel": [],
        "touchstart": [],
        "touchend": [],
        "touchmove": [],
        "scroll": [],
        "keydown": [],
        "keyup": [],
        "resize": [],
        "paste": []
    },
    "sdk": {
        "caller_stack_trace": ""
    },
    "s": 883755726
}